mroudai_django_providers-0.1.0.dist-info/licenses/LICENSE
providers/__init__.py
providers/admin.py
providers/apps.py
providers/conf.py
providers/models.py
providers/selectors.py
providers/migrations/0001_initial.py
providers/migrations/__init__.py
providers/tests/__init__.py
providers/tests/settings.py
providers/tests/settings_tenants.py
providers/tests/test_models.py
providers/tests/services/__init__.py
providers/tests/services/apps.py
providers/tests/services/models.py
providers/tests/services/migrations/0001_initial.py
providers/tests/services/migrations/__init__.py
providers/tests/tenants/__init__.py
providers/tests/tenants/apps.py
providers/tests/tenants/models.py
providers/tests/tenants/migrations/0001_initial.py
providers/tests/tenants/migrations/__init__.py
mroudai_django_providers-0.1.0.dist-info/METADATA
mroudai_django_providers-0.1.0.dist-info/WHEEL
mroudai_django_providers-0.1.0.dist-info/top_level.txt
mroudai_django_providers-0.1.0.dist-info/RECORD
